umie_datasets/base/__init__.py
umie_datasets/base/extractors/__init__.py
umie_datasets/base/extractors/img_id.py
umie_datasets/base/extractors/label.py
umie_datasets/base/extractors/phase_id.py
umie_datasets/base/extractors/study_id.py
umie_datasets/base/pipeline.py
umie_datasets/base/step.py
umie_datasets/config/__init__.py
umie_datasets/config/dataset_config.py
umie_datasets/config/labels.py
umie_datasets/config/masks.py
umie_datasets/config/runner_config.py
umie_datasets/constants.py
umie_datasets/pipelines/__init__.py
umie_datasets/pipelines/alzheimers.py
umie_datasets/pipelines/brain_met_share.py
umie_datasets/pipelines/brain_tumor_classification.py
umie_datasets/pipelines/brain_tumor_detection.py
umie_datasets/pipelines/brain_tumor_progression.py
umie_datasets/pipelines/brain_with_intracranial_hemorrhage.py
umie_datasets/pipelines/chest_xray14.py
umie_datasets/pipelines/coca.py
umie_datasets/pipelines/coronahack.py
umie_datasets/pipelines/covid19_detection.py
umie_datasets/pipelines/finding_and_measuring_lungs.py
umie_datasets/pipelines/kits23.py
umie_datasets/pipelines/knee_osteoarthritis.py
umie_datasets/pipelines/lits.py
umie_datasets/steps/__init__.py
umie_datasets/steps/add_labels.py
umie_datasets/steps/add_umie_ids.py
umie_datasets/steps/combine_multiple_masks.py
umie_datasets/steps/convert_dcm2png.py
umie_datasets/steps/convert_jpg2png.py
umie_datasets/steps/convert_nii2png.py
umie_datasets/steps/convert_tif2png.py
umie_datasets/steps/copy_masks.py
umie_datasets/steps/create_blank_masks.py
umie_datasets/steps/create_file_tree.py
umie_datasets/steps/create_masks_from_xml.py
umie_datasets/steps/delete_imgs_with_no_annotations.py
umie_datasets/steps/delete_temp_files.py
umie_datasets/steps/delete_temp_png.py
umie_datasets/steps/get_file_paths.py
umie_datasets/steps/masks_to_binary_colors.py
umie_datasets/steps/recolor_masks.py
umie_datasets/steps/store_source_paths.py
umie_datasets-0.1.4.dist-info/METADATA
umie_datasets-0.1.4.dist-info/WHEEL
umie_datasets-0.1.4.dist-info/RECORD
