Metadata-Version: 2.1
Name: umie-datasets
Version: 0.1.4
Summary: 
Author: a-huli
Author-email: klaudel.b@gmail.com
Requires-Python: >=3.11,<4.0
Classifier: Programming Language :: Python :: 3
Classifier: Programming Language :: Python :: 3.11
Requires-Dist: Pillow (>=10.0.0,<11.0.0)
Requires-Dist: datasets (>=2.20.0,<3.0.0)
Requires-Dist: jsonlines (>=4.0.0,<5.0.0)
Requires-Dist: nibabel (>=5.2.0,<6.0.0)
Requires-Dist: numpy (>=1.26.4,<2.0.0)
Requires-Dist: opencv-python (>=4.8.0.74,<5.0.0.0)
Requires-Dist: pandas (>=2.1.3,<3.0.0)
Requires-Dist: pyaml (>=23.9.7,<24.0.0)
Requires-Dist: pydicom (>=2.4.3,<3.0.0)
Requires-Dist: pyyaml (>=6.0.1,<7.0.0)
Requires-Dist: scikit-learn (>=1.3.2,<2.0.0)
Requires-Dist: tqdm (>=4.66.1,<5.0.0)
Requires-Dist: types-pyyaml (>=6.0.12.12,<7.0.0.0)
Requires-Dist: untangle (>=1.2.1,<2.0.0)
